regions/conftest.py
regions/version.py
regions/compiler_version.abi3.so
regions/__init__.py
regions/CITATION.rst
regions/_utils/__init__.py
regions/_utils/examples.py
regions/_utils/optional_deps.py
regions/_utils/wcs_helpers.py
regions/_utils/tests/__init__.py
regions/_utils/tests/test_examples.py
regions/core/mask.py
regions/core/metadata.py
regions/core/pixcoord.py
regions/core/attributes.py
regions/core/registry.py
regions/core/regions.py
regions/core/__init__.py
regions/core/core.py
regions/core/compound.py
regions/core/bounding_box.py
regions/core/tests/test_mask.py
regions/core/tests/test_bounding_box.py
regions/core/tests/test_pixcoord.py
regions/core/tests/test_metadata.py
regions/core/tests/__init__.py
regions/core/tests/test_regions.py
regions/core/tests/test_compound.py
regions/io/__init__.py
regions/io/ds9/write.py
regions/io/ds9/connect.py
regions/io/ds9/__init__.py
regions/io/ds9/core.py
regions/io/ds9/read.py
regions/io/ds9/meta.py
regions/io/ds9/tests/__init__.py
regions/io/ds9/tests/test_ds9.py
regions/io/ds9/tests/data/ds9.fk4.hms.reg
regions/io/ds9/tests/data/ds9.image.reg
regions/io/ds9/tests/data/ds9.galactic.hms.reg
regions/io/ds9/tests/data/galactic_reference.reg
regions/io/ds9/tests/data/ds9.fk5.hms.reg
regions/io/ds9/tests/data/ds9.ecliptic.hms.reg
regions/io/ds9/tests/data/ds9.color.spaces.reg
regions/io/ds9/tests/data/ds9.icrs.hms.reg
regions/io/ds9/tests/data/ds9.color.reg
regions/io/ds9/tests/data/fk5_reference.reg
regions/io/ds9/tests/data/ds9.fits.reg
regions/io/ds9/tests/data/ds9.composite.reg
regions/io/ds9/tests/data/ds9.galactic.reg
regions/io/ds9/tests/data/plot_image.reg
regions/io/ds9/tests/data/ds9.ecliptic.reg
regions/io/ds9/tests/data/ds9.icrs.oneline.reg
regions/io/ds9/tests/data/ds9.icrs.reg
regions/io/ds9/tests/data/ds9.image.oneline.reg
regions/io/ds9/tests/data/ds9.fk5.reg
regions/io/ds9/tests/data/ds9.fk4.reg
regions/io/fits/write.py
regions/io/fits/connect.py
regions-0.11.dist-info/RECORD
regions-0.11.dist-info/WHEEL
regions-0.11.dist-info/top_level.txt
regions-0.11.dist-info/METADATA
regions-0.11.dist-info/licenses/LICENSE.rst
