Metadata-Version: 2.4
Name: regions
Version: 0.11
Summary: An Astropy coordinated package for region handling
Author-email: Regions Developers <astropy.team@gmail.com>
License-Expression: BSD-3-Clause
Project-URL: Homepage, https://github.com/astropy/regions
Project-URL: Documentation, https://astropy-regions.readthedocs.io/en/stable/
Keywords: astronomy,astrophysics,astropy,regions
Classifier: Intended Audience :: Science/Research
Classifier: Natural Language :: English
Classifier: Operating System :: OS Independent
Classifier: Programming Language :: Cython
Classifier: Programming Language :: Python
Classifier: Programming Language :: Python :: 3
Classifier: Topic :: Scientific/Engineering :: Astronomy
Requires-Python: >=3.11
License-File: LICENSE.rst
Requires-Dist: numpy>=1.25
Requires-Dist: astropy>=6.0
Provides-Extra: all
Requires-Dist: matplotlib>=3.8; extra == "all"
Requires-Dist: shapely>=2.0.0; extra == "all"
Provides-Extra: test
Requires-Dist: pytest-astropy>=0.11; extra == "test"
Requires-Dist: pytest-xdist>=2.5.0; extra == "test"
Requires-Dist: pytest-arraydiff>=0.6.1; extra == "test"
Requires-Dist: tox>4.0; extra == "test"
Provides-Extra: docs
Requires-Dist: regions[all]; extra == "docs"
Requires-Dist: sphinx; extra == "docs"
Requires-Dist: sphinx-astropy>=1.9; extra == "docs"
Provides-Extra: dev
Requires-Dist: regions[docs,test]; extra == "dev"
Requires-Dist: pre-commit>4.0; extra == "dev"
Dynamic: license-file
